CommonzZ/__init__.py
CommonzZ/config.py
CommonzZ/hash.py
CommonzZ/http_util.py
CommonzZ/logger.py
CommonzZ/singleton.py
CommonzZ/crypto/__init__.py
CommonzZ/crypto/aes.py
CommonzZ/crypto/rsa.py
CommonzZ-0.0.1.dist-info/METADATA
CommonzZ-0.0.1.dist-info/WHEEL
CommonzZ-0.0.1.dist-info/top_level.txt
CommonzZ-0.0.1.dist-info/RECORD
